Metadata-Version: 1.0
Name: htpackage
Version: 1.0
Summary: Package with modifications of Hough transform
Home-page: UNKNOWN
Author: UNKNOWN
Author-email: michadas5@gmail.com
License: UNKNOWN
Platform: UNKNOWN
